{
    "Stations": [
        {
            "Code": "LULUX",
            "Name": "Luxembourg",
            "OpeningHours": "",
            "FloorPlanDownloadURL": "https://static.accept.b-europe.com/-/media/MediaRepository/Files/Station_Plans/LULUX/Map_Gare-de-Luxembourg.ashx",
            "MoreDetailsURL": "",
            "Longitude": "6.133923",
            "Latitude": "49.600024",
            "Street": "Place de la Gare",
            "Number": "11",
            "PostalCode": "1616",
            "City": "Luxembourg",
            "Country": "Luxembourg",
            "StationInfos": [
                {
                    "Title": "Travel and tourist information services",
                    "Content": "Luxembourg central station is the ideal station to start your journey to Germany, Belgium and France and other European destinations. Connected by direct TGV to Paris, Strasbourg, Montpellier and Marseille.",
                    "Image": "https://static.accept.b-europe.com/-/media/CFL/StationInfo/Luxembourg.ashx"
                }
            ],
            "Parkings": [
                {
                    "Title": "Parking",
                    "Content": "Car park Luxembourg-Gare near the station.  Open 24/7.",
                    "Address": "Place de la gare, L-1616 Luxembourg",
                    "Latitude": "49.5991488",
                    "Longitude": "6.131214"
                }
            ],
            "StationFacilities": [
                {
                    "Title": "Wi-Fi"
                },
                {
                    "Title": "Shops"
                },
                {
                    "Title": "Cash machines"
                },
                {
                    "Title": "Facilities for disabled persons."
                },
                {
                    "Title": "Restaurants"
                },
                {
                    "Title": "Carsharing"
                },
                {
                    "Title": "Taxi Stack"
                },
                {
                    "Title": "Waiting room"
                },
                {
                    "Title": "Public transport"
                },
                {
                    "Title": "Luggage storage"
                },
                {
                    "Title": "Showers & restrooms"
                }
            ]
        },
        {
            "Code": "BEBMI",
            "Name": "Bruxelles-Midi/Brussel-Zuid",
            "OpeningHours": "",
            "FloorPlanDownloadURL": "https://static.accept.b-europe.com/-/media/MediaRepository/Files/Station_Plans/BEBMI/MAP_Brussels-Midi_EN_Optimized.ashx",
            "MoreDetailsURL": "",
            "Longitude": "4.333527",
            "Latitude": "50.8357532",
            "Street": "Rue de France",
            "Number": "",
            "PostalCode": "1060",
            "City": "Brussels",
            "Country": "Belgium",
            "StationInfos": [
                {
                    "Title": "Bruxelles-Midi/Brussel-Zuid (Brussels) train station",
                    "Content": "Bruxelles-Midi/Brussel-Zuid train station, served by Thalys, Eurostar, TGV®, and ICE trains, is the ideal starting point for your journeys to Germany, France, The Netherlands, Luxembourg and the United Kingdom and connects travellers to the entire Belgian domestic railway network.",
                    "Image": ""
                },
                {
                    "Title": "Travel and tourist information services",
                    "Content": "At Bruxelles-Midi/Brussel-Zuid train station, you'll find several information desks for domestic and international travel, as well as an international Thalys info desk and a a Brussels Tourist Office desk.",
                    "Image": "https://static.accept.b-europe.com/-/media/ImagesNew/Mobile/Brussel_Zuid_Mob.ashx"
                }
            ],
            "Parkings": [
                {
                    "Title": "Q-Park \"Gare du Midi\"",
                    "Content": "Direct access to Brussel-Zuid/Bruxelles-Midi (Brussels) train station. Open 24/7.",
                    "Address": "40, Rue de France, 1060 Brussels",
                    "Latitude": "50.834617",
                    "Longitude": "4.3307218"
                }
            ],
            "StationFacilities": [
                {
                    "Title": "Wi-Fi"
                },
                {
                    "Title": "Waiting rooms and lounges"
                },
                {
                    "Title": "Shops"
                },
                {
                    "Title": "Cash machines"
                },
                {
                    "Title": "Facilities for mobility-impaired passengers"
                },
                {
                    "Title": "Restaurants"
                },
                {
                    "Title": "Car rental and bicycle hire"
                },
                {
                    "Title": "Taxi"
                },
                {
                    "Title": "Public transport"
                },
                {
                    "Title": "Restrooms"
                }
            ]
        },
        {
            "Code": "DEDUH",
            "Name": "Düsseldorf Hbf",
            "OpeningHours": "",
            "FloorPlanDownloadURL": "https://static.accept.b-europe.com/-/media/MediaRepository/Files/Station_Plans/DEDUH/MAP_Duesseldorf.ashx",
            "MoreDetailsURL": "",
            "Longitude": "6.7929443",
            "Latitude": "51.2202453",
            "Street": "",
            "Number": "",
            "PostalCode": "",
            "City": "",
            "Country": "",
            "StationInfos": [
                {
                    "Title": "Travel and tourist information services",
                    "Content": "The city’s main train station is situated on Germany’s busiest rail line . More than 300 regional and InterCity trains stops here.",
                    "Image": "https://static.accept.b-europe.com/-/media/CFL/StationInfo/Duesseldorf.ashx"
                }
            ],
            "Parkings": [
                {
                    "Title": "Vorplatz Düsseldorf Hbf",
                    "Content": "Open 24/7",
                    "Address": "Konrad-Adenauer-Platz 13-14, 40227 Düsseldorf",
                    "Latitude": "51.2196071",
                    "Longitude": "6.7890726"
                },
                {
                    "Title": "Parkhaus am Hauptbahnhof",
                    "Content": "Open 24/7",
                    "Address": "Charlottenstr. 62, 40210 Düsseldorf",
                    "Latitude": "51.2216162",
                    "Longitude": "6.7861244"
                }
            ],
            "StationFacilities": [
                {
                    "Title": "Wi-Fi"
                },
                {
                    "Title": "Shops"
                },
                {
                    "Title": "Facilities for disabled persons"
                },
                {
                    "Title": "Car rental"
                },
                {
                    "Title": "Waiting room"
                },
                {
                    "Title": "DB Lounge"
                },
                {
                    "Title": "Luggage storage"
                },
                {
                    "Title": "Taxi"
                },
                {
                    "Title": "Public transport"
                },
                {
                    "Title": "Restrooms"
                }
            ]
        },
        {
            "Code": "FRPST",
            "Name": "Paris Est",
            "OpeningHours": "",
            "FloorPlanDownloadURL": "https://static.accept.b-europe.com/-/media/MediaRepository/Files/Station_Plans/FRPST/MAP_Paris-est.ashx",
            "MoreDetailsURL": "",
            "Longitude": "2.3562452",
            "Latitude": "48.876389",
            "Street": "",
            "Number": "",
            "PostalCode": "",
            "City": "",
            "Country": "",
            "StationInfos": [
                {
                    "Title": "Travel and tourist information services",
                    "Content": "The Gare de l'Est, is one of the six large SNCF terminal stations in the Capital of France. It is not far from the Gare du Nord.",
                    "Image": "https://static.accept.b-europe.com/-/media/CFL/StationInfo/PARIS.ashx"
                }
            ],
            "Parkings": [
                {
                    "Title": "Parking \"P1\"",
                    "Content": "Entrance by rue du 8 Mai 1945",
                    "Address": "Rue du 8 Mai 1945, 75010 Paris",
                    "Latitude": "48.876389",
                    "Longitude": "2.3562452"
                },
                {
                    "Title": "Parking \"P2 Saint Martin\"",
                    "Content": "Entrance by rue du Faubourg Saint-Martin.",
                    "Address": "Rue du Faubourg Saint-Martin., 75010 Paris",
                    "Latitude": "48.876389",
                    "Longitude": "2.3562452"
                }
            ],
            "StationFacilities": [
                {
                    "Title": "Wi-Fi"
                },
                {
                    "Title": "Shops"
                },
                {
                    "Title": "Restaurants"
                },
                {
                    "Title": "Facilities for mobility-impaired passengers"
                },
                {
                    "Title": "Luggage storage"
                },
                {
                    "Title": "Public transport"
                },
                {
                    "Title": "Waiting room"
                },
                {
                    "Title": "Vending machine"
                },
                {
                    "Title": "Taxi"
                },
                {
                    "Title": "Car rental"
                },
                {
                    "Title": "Restrooms"
                }
            ]
        },
        {
            "Code": "FRAEG",
            "Name": "Strasbourg",
            "OpeningHours": "",
            "FloorPlanDownloadURL": "https://static.accept.b-europe.com/-/media/MediaRepository/Files/Station_Plans/FRAEG/MAP_Strasbourg.ashx",
            "MoreDetailsURL": "",
            "Longitude": "7.7325305",
            "Latitude": "48.5864966",
            "Street": "",
            "Number": "",
            "PostalCode": "",
            "City": "",
            "Country": "",
            "StationInfos": [
                {
                    "Title": "Travel and tourist information services",
                    "Content": "Strasbourg train station offers travelers a wide range of connections to other regions in France.",
                    "Image": "https://static.accept.b-europe.com/-/media/CFL/StationInfo/Strasbourg.ashx"
                }
            ],
            "Parkings": [
                {
                    "Title": "Short Time parking",
                    "Content": "Open 24/7",
                    "Address": "20, place de la gare, 67000 Strasbourg",
                    "Latitude": "48.5850036",
                    "Longitude": "7.7321784"
                },
                {
                    "Title": "Short Time parking",
                    "Content": "Open 24/7",
                    "Address": "20, place de la gare, 67000 Strasbourg",
                    "Latitude": "48.5828334",
                    "Longitude": "7.7305166"
                }
            ],
            "StationFacilities": [
                {
                    "Title": "Wi-Fi"
                },
                {
                    "Title": "Shops"
                },
                {
                    "Title": "Restaurants"
                },
                {
                    "Title": "Facilities for mobility-impaired passengers"
                },
                {
                    "Title": "Luggage storage"
                },
                {
                    "Title": "Public transport"
                },
                {
                    "Title": "Waiting room"
                },
                {
                    "Title": "Taxi"
                },
                {
                    "Title": "Car rental"
                },
                {
                    "Title": "Restrooms"
                }
            ]
        },
        {
            "Code": "FRMPL",
            "Name": "Montpellier",
            "OpeningHours": "",
            "FloorPlanDownloadURL": "",
            "MoreDetailsURL": "",
            "Longitude": "3.8942964",
            "Latitude": "43.599435",
            "Street": "",
            "Number": "",
            "PostalCode": "",
            "City": "",
            "Country": "",
            "StationInfos": [
                {
                    "Title": "Travel and tourist information services",
                    "Content": "The station of Montpellier Saint Roch is one of the most important stations in the South of France. Arrival point for several TGV services. Daily direct service from Luxembourg.",
                    "Image": "https://static.accept.b-europe.com/-/media/CFL/StationInfo/Montpellier.ashx"
                }
            ],
            "Parkings": [
                {
                    "Title": "Parking \"Saint-Roch\"",
                    "Content": "Open 24/7",
                    "Address": "101, rue Alexandra David Néel, 34011 Montpellier",
                    "Latitude": "43.6039452",
                    "Longitude": "3.877285"
                }
            ],
            "StationFacilities": [
                {
                    "Title": "Wi-Fi"
                },
                {
                    "Title": "Shops"
                },
                {
                    "Title": "Restaurants"
                },
                {
                    "Title": "Facilities for mobility-impaired passengers"
                },
                {
                    "Title": "Luggage storage"
                },
                {
                    "Title": "Public transport"
                },
                {
                    "Title": "Waiting room"
                },
                {
                    "Title": "Vending Machine"
                },
                {
                    "Title": "Carsharing"
                },
                {
                    "Title": "Taxi"
                },
                {
                    "Title": "Car rental"
                },
                {
                    "Title": "Bank"
                },
                {
                    "Title": "Restrooms"
                }
            ]
        },
        {
            "Code": "GBSPX",
            "Name": "London St Pancras International",
            "OpeningHours": "",
            "FloorPlanDownloadURL": "https://static.accept.b-europe.com/-/media/MediaRepository/Files/Station_Plans/GBSPX/MAP_London_Optimized_EN.ashx",
            "MoreDetailsURL": "",
            "Longitude": "-0.125468",
            "Latitude": "51.53022",
            "Street": "Euston Road",
            "Number": "",
            "PostalCode": "N1C 4QP",
            "City": "London",
            "Country": "United Kingdom",
            "StationInfos": [
                {
                    "Title": "London St Pancras International train station",
                    "Content": "London's St Pancras International Station is where major domestic railway lines terminate and Eurostar starts. Making this railway station the gateway to Continental Europe.",
                    "Image": ""
                },
                {
                    "Title": "Travel and tourist information services",
                    "Content": "London St Pancras International train station features several information desks, among which you'll find information desks for national and international travel.",
                    "Image": "https://static.accept.b-europe.com/-/media/CFL/StationInfo/Londres.ashx"
                }
            ],
            "Parkings": [
                {
                    "Title": "St Pancras International Parking",
                    "Content": "Car park near London St Pancras International. Open 24/7.",
                    "Address": "Pancras Road, Londen, N1C 4TB",
                    "Latitude": "51.5334761",
                    "Longitude": "-0.1308258"
                }
            ],
            "StationFacilities": [
                {
                    "Title": "Wi-Fi"
                },
                {
                    "Title": "Waiting rooms and lounges"
                },
                {
                    "Title": "Shops"
                },
                {
                    "Title": "Cash machines"
                },
                {
                    "Title": "Facilities for mobility-impaired passengers"
                },
                {
                    "Title": "Restaurants"
                },
                {
                    "Title": "Car rental and bicycle hire"
                },
                {
                    "Title": "Taxi"
                },
                {
                    "Title": "Public transport"
                },
                {
                    "Title": "Restrooms"
                }
            ]
        }
    ],
    "Messages": [],
    "DebugMessages": []
}
